{
    "added": {
        "3.3": [
            "MappingProxyType",
            "SimpleNamespace",
            "new_class",
            "prepare_class"
        ],
        "3.4": [
            "DynamicClassAttribute"
        ],
        "3.5": [
            "CoroutineType",
            "coroutine"
        ],
        "3.6": [
            "AsyncGeneratorType"
        ],
        "3.7": [
            "ClassMethodDescriptorType",
            "MethodDescriptorType",
            "MethodWrapperType",
            "WrapperDescriptorType",
            "resolve_bases"
        ],
        "3.8": [
            "CellType"
        ],
        "3.9": [
            "GenericAlias"
        ],
        "3.10": [
            "EllipsisType",
            "NoneType",
            "NotImplementedType",
            "UnionType"
        ]
    }
}