{
  "_thread": {
    "added": {
      "Python 3.2": [
        "TIMEOUT_MAX"
      ],
      "Python 3.8": [
        "get_native_id"
      ]
    }
  },
  "abc": {
    "added": {
      "Python 3.2": [
        "abstractclassmethod",
        "abstractstaticmethod"
      ],
      "Python 3.4": [
        "ABC",
        "get_cache_token"
      ],
      "Python 3.10": [
        "update_abstractmethods"
      ]
    }
  },
  "argparse": {
    "created": "Python 3.2",
    "added": {
      "Python 3.9": [
        "BooleanOptionalAction"
      ]
    }
  },
  "ast": {
    "added": {
      "Python 3.6": [
        "Constant"
      ],
      "Python 3.8": [
        "PyCF_ALLOW_TOP_LEVEL_AWAIT",
        "PyCF_TYPE_COMMENTS",
        "get_source_segment"
      ],
      "Python 3.9": [
        "unparse"
      ]
    }
  },
  "asyncio": {
    "created": "Python 3.4",
    "added": {
      "Python 3.6": [
        "run_coroutine_threadsafe",
        "loop.shutdown_asyncgens"
      ],
      "Python 3.7": [
        "BufferedProtocol",
        "all_tasks",
        "create_task",
        "current_task",
        "get_running_loop",
        "run"
      ],
      "Python 3.9": [
        "PidfdChildWatcher",
        "loop.shutdown_default_executor",
        "to_thread"
      ],
      "Python 3.11": [
        "Barrier",
        "BrokenBarrierError",
        "Runner",
        "TaskGroup",
        "Timeout",
        "timeout"
      ]
    }
  },
  "audioop": {
    "added": {
      "Python 3.4": [
        "byteswap"
      ]
    }
  },
  "base64": {
    "added": {
      "Python 3.1": [
        "decodebytes",
        "encodebytes"
      ],
      "Python 3.4": [
        "a85encode",
        "a85decode",
        "b85encode",
        "b85decode"
      ],
      "Python 3.10": [
        "b32hexencode",
        "b32hexdecode"
      ]
    }
  },
  "bytearray": {
    "added": {
      "Python 3.1": [
        "maketrans"
      ]
    }
  },
  "bytes": {
    "added": {
      "Python 3.1": [
        "maketrans"
      ]
    }
  },
  "bz2": {
    "added": {
      "Python 3.3": [
        "open"
      ]
    }
  },
  "cmath": {
    "added": {
      "Python 3.2": [
        "isfinite"
      ],
      "Python 3.5": [
        "isclose"
      ],
      "Python 3.6": [
        "tau",
        "inf",
        "infj",
        "nan",
        "nanj"
      ]
    }
  },
  "codecs": {
    "added": {
      "Python 3.5": [
        "namereplace_errors"
      ],
      "Python 3.10": [
        "unregister"
      ]
    }
  },
  "collections": {
    "added": {
      "Python 3.1": [
        "Counter",
        "OrderedDict"
      ],
      "Python 3.3": [
        "ChainMap"
      ]
    }
  },
  "collections.abc": {
    "created": "Python 3.3",
    "added": {
      "Python 3.5": [
        "AsyncIterable",
        "AsyncIterator",
        "Awaitable",
        "Coroutine",
        "Generator"
      ],
      "Python 3.6": [
        "AsyncGenerator",
        "Collection",
        "Reversible"
      ]
    }
  },
  "concurrent.futures": {
    "created": "Python 3.2",
    "added": {
      "Python 3.7": [
        "BrokenExecutor"
      ],
      "Python 3.8": [
        "InvalidStateError"
      ]
    }
  },
  "concurrent.futures.process": {
    "added": {
      "Python 3.3": [
        "BrokenProcessPool"
      ]
    }
  },
  "concurrent.futures.thread": {
    "added": {
      "Python 3.7": [
        "thread.BrokenThreadPool"
      ]
    }
  },
  "contextlib": {
    "added": {
      "Python 3.2": [
        "ContextDecorator"
      ],
      "Python 3.3": [
        "ExitStack"
      ],
      "Python 3.4": [
        "redirect_stdout",
        "suppress"
      ],
      "Python 3.5": [
        "redirect_stderr"
      ],
      "Python 3.6": [
        "AbstractContextManager"
      ],
      "Python 3.7": [
        "AbstractAsyncContextManager",
        "AsyncExitStack",
        "asynccontextmanager",
        "nullcontext"
      ],
      "Python 3.10": [
        "AsyncContextDecorator",
        "aclosing"
      ],
      "Python 3.11": [
        "chdir"
      ]
    }
  },
  "contextvars": {
    "created": "Python 3.7"
  },
  "crypt": {
    "added": {
      "Python 3.3": [
        "METHOD_SHA256",
        "METHOD_SHA512",
        "METHOD_MD5",
        "METHOD_CRYPT",
        "methods",
        "mksalt"
      ],
      "Python 3.7": [
        "METHOD_BLOWFISH"
      ]
    }
  },
  "csv": {
    "added": {
      "Python 3.2": [
        "unix_dialect"
      ]
    }
  },
  "ctypes": {
    "added": {
      "Python 3.2": [
        "c_ssize_t"
      ],
      "Python 3.11": [
        "BigEndianUnion",
        "LittleEndianUnion"
      ]
    }
  },
  "curses": {
    "added": {
      "Python 3.3": [
        "unget_wch"
      ],
      "Python 3.5": [
        "update_lines_cols"
      ],
      "Python 3.7": [
        "A_ITALIC"
      ],
      "Python 3.8": [
        "ncurses_version"
      ],
      "Python 3.9": [
        "get_escdelay",
        "set_escdelay",
        "get_tabsize",
        "set_tabsize"
      ],
      "Python 3.10": [
        "has_extended_color_support"
      ]
    }
  },
  "dataclasses": {
    "created": "Python 3.7",
    "added": {
      "Python 3.10": [
        "KW_ONLY"
      ]
    }
  },
  "datetime": {
    "added": {
      "Python 3.2": [
        "datetime.timezone"
      ],
      "Python 3.3": [
        "datetime.timestamp"
      ],
      "Python 3.7": [
        "datetime.fromisoformat"
      ],
      "Python 3.8": [
        "date.fromisocalendar",
        "datetime.fromisocalendar"
      ],
      "Python 3.11": [
        "datetime.UTC"
      ]
    }
  },
  "dis": {
    "added": {
      "Python 3.2": [
        "code_info",
        "show_code"
      ],
      "Python 3.4": [
        "Bytecode",
        "Instruction",
        "get_instructions",
        "stack_effect"
      ],
      "Python 3.11": [
        "Positions"
      ],
      "Python 3.12": [
        "hasarg"
      ]
    }
  },
  "doctest": {
    "added": {
      "Python 3.4": [
        "FAIL_FAST"
      ]
    }
  },
  "email": {
    "added": {
      "Python 3.4": [
        "as_bytes"
      ]
    }
  },
  "ensurepip": {
    "created": "Python 3.4"
  },
  "enum": {
    "created": "Python 3.4",
    "added": {
      "Python 3.6": [
        "Flag",
        "IntFlag",
        "auto"
      ],
      "Python 3.11": [
        "EnumCheck",
        "EnumType",
        "FlagBoundary",
        "ReprEnum",
        "StrEnum",
        "global_enum",
        "member",
        "nonmember",
        "property",
        "show_flag_values",
        "verify"
      ]
    }
  },
  "faulthandler": {
    "created": "Python 3.3"
  },
  "fcntl": {
    "added": {
      "Python 3.8": [
        "F_ADD_SEALS",
        "F_GET_SEALS",
        "F_SEAL_GROW",
        "F_SEAL_SHRINK",
        "F_SEAL_SEAL",
        "F_SEAL_WRITE"
      ],
      "Python 3.9": [
        "F_GETPATH",
        "F_OFD_GETLK",
        "F_OFD_SETLK",
        "F_OFD_SETLKW"
      ],
      "Python 3.10": [
        "F_GETPIPE_SZ",
        "F_SETPIPE_SZ"
      ],
      "Python 3.11": [
        "F_DUP2FD",
        "F_DUP2FD_CLOEXEC"
      ]
    }
  },
  "filecmp": {
    "added": {
      "Python 3.4": [
        "DEFAULT_IGNORES",
        "clear_cache"
      ]
    }
  },
  "functools": {
    "added": {
      "Python 3.2": [
        "cmp_to_key",
        "lru_cache",
        "total_ordering"
      ],
      "Python 3.4": [
        "partialmethod",
        "singledispatch"
      ],
      "Python 3.8": [
        "cached_property",
        "singledispatchmethod"
      ],
      "Python 3.9": [
        "cache"
      ]
    }
  },
  "gc": {
    "added": {
      "Python 3.1": [
        "is_tracked"
      ],
      "Python 3.3": [
        "callbacks"
      ],
      "Python 3.4": [
        "get_stats"
      ],
      "Python 3.7": [
        "freeze",
        "unfreeze",
        "get_freeze_count"
      ],
      "Python 3.9": [
        "is_finalized"
      ]
    }
  },
  "gettext": {
    "added": {
      "Python 3.8": [
        "pgettext",
        "dpgettext",
        "npgettext",
        "dnpgettext"
      ]
    }
  },
  "glob": {
    "added": {
      "Python 3.4": [
        "escape"
      ]
    }
  },
  "graphlib": {
    "created": "Python 3.9"
  },
  "gzip": {
    "added": {
      "Python 3.2": [
        "compress",
        "decompress"
      ],
      "Python 3.8": [
        "BadGzipFile"
      ]
    }
  },
  "hashlib": {
    "added": {
      "Python 3.2": [
        "algorithms_available",
        "algorithms_guaranteed"
      ],
      "Python 3.4": [
        "pbkdf2_hmac"
      ],
      "Python 3.6": [
        "blake2b",
        "blake2s",
        "sha3_224",
        "sha3_256",
        "sha3_384",
        "sha3_512",
        "shake_128",
        "shake_256",
        "scrypt"
      ],
      "Python 3.11": [
        "file_digest"
      ]
    }
  },
  "hmac": {
    "added": {
      "Python 3.3": [
        "compare_digest"
      ],
      "Python 3.4": [
        "block_size",
        "name"
      ],
      "Python 3.7": [
        "digest"
      ]
    }
  },
  "html": {
    "added": {
      "Python 3.2": [
        "escape"
      ],
      "Python 3.3": [
        "entities.html5"
      ],
      "Python 3.4": [
        "unescape"
      ]
    }
  },
  "html.entities": {
    "added": {
      "Python 3.3": [
        "html5"
      ]
    }
  },
  "http": {
    "added": {
      "Python 3.5": [
        "HTTPStatus"
      ],
      "Python 3.11": [
        "HTTPMethod"
      ]
    }
  },
  "http.client": {
    "added": {
      "Python 3.5": [
        "RemoteDisconnected"
      ]
    }
  },
  "http.server": {
    "added": {
      "Python 3.7": [
        "ThreadingHTTPServer"
      ]
    }
  },
  "importlib": {
    "created": "Python 3.1",
    "added": {
      "Python 3.3": [
        "find_loader",
        "invalidate_caches"
      ],
      "Python 3.4": [
        "reload"
      ],
      "Python 3.9": [
        "resources.files",
        "resources.as_file"
      ]
    }
  },
  "importlib.abc": {
    "added": {
      "Python 3.3": [
        "MetaPathFinder",
        "PathEntryFinder",
        "FileLoader"
      ]
    }
  },
  "importlib.machinery": {
    "added": {
      "Python 3.3": [
        "SOURCE_SUFFIXES",
        "DEBUG_BYTECODE_SUFFIXES",
        "OPTIMIZED_BYTECODE_SUFFIXES",
        "BYTECODE_SUFFIXES",
        "EXTENSION_SUFFIXES",
        "WindowsRegistryFinder",
        "FileFinder",
        "SourceFileLoader",
        "SourcelessFileLoader",
        "ExtensionFileLoader",
        "all_suffixes"
      ],
      "Python 3.4": [
        "ModuleSpec"
      ],
      "Python 3.5": [
        "module_from_spec"
      ]
    }
  },
  "importlib.metadata": {
    "created": "Python 3.8",
    "added": {
      "Python 3.10": [
        "packages_distributions"
      ]
    }
  },
  "importlib.resources": {
    "created": "Python 3.7",
    "added": {
      "Python 3.9": [
        "files",
        "as_file"
      ]
    }
  },
  "importlib.resources.abc": {
    "created": "Python 3.11"
  },
  "importlib.util": {
    "added": {
      "Python 3.3": [
        "resolve_name"
      ],
      "Python 3.4": [
        "MAGIC_NUMBER",
        "cache_from_source",
        "source_from_cache",
        "decode_source",
        "find_spec",
        "spec_from_loader",
        "spec_from_file_location"
      ],
      "Python 3.5": [
        "LazyLoader"
      ],
      "Python 3.7": [
        "source_hash"
      ]
    }
  },
  "inspect": {
    "added": {
      "Python 3.2": [
        "getattr_static",
        "getcallargs",
        "getgeneratorstate"
      ],
      "Python 3.3": [
        "BoundArguments",
        "Parameter",
        "Signature",
        "signature",
        "getclosurevars",
        "getgeneratorlocals"
      ],
      "Python 3.4": [
        "unwrap"
      ],
      "Python 3.5": [
        "CO_COROUTINE",
        "CO_ITERABLE_COROUTINE",
        "getcoroutinelocals",
        "getcoroutinestate",
        "isawaitable",
        "iscoroutine",
        "iscoroutinefunction"
      ],
      "Python 3.6": [
        "CO_ASYNC_GENERATOR",
        "isasyncgen",
        "isasyncgenfunction"
      ],
      "Python 3.10": [
        "get_annotations"
      ],
      "Python 3.11": [
        "getmembers_static",
        "ismethodwrapper"
      ],
      "Python 3.12": [
        "markcoroutinefunction"
      ]
    }
  },
  "inspect.machinery": {
    "added": {
      "Python 3.11": [
        "NamespaceLoader"
      ]
    }
  },
  "io": {
    "added": {
      "Python 3.1": [
        "SEEK_SET",
        "SEEK_CUR",
        "SEEK_END"
      ],
      "Python 3.8": [
        "open_code"
      ],
      "Python 3.10": [
        "text_encoding"
      ]
    }
  },
  "ipaddress": {
    "created": "Python 3.3"
  },
  "itertools": {
    "added": {
      "Python 3.1": [
        "combinations_with_replacement",
        "compress"
      ],
      "Python 3.2": [
        "accumulate"
      ],
      "Python 3.10": [
        "pairwise"
      ]
    }
  },
  "json": {
    "added": {
      "Python 3.5": [
        "JSONDecodeError"
      ]
    }
  },
  "keyword": {
    "added": {
      "Python 3.9": [
        "issoftkeyword",
        "softkwlist"
      ]
    }
  },
  "linecache": {
    "added": {
      "Python 3.5": [
        "lazycache"
      ]
    }
  },
  "locale": {
    "added": {
      "Python 3.5": [
        "delocalize"
      ],
      "Python 3.10": [
        "localize"
      ],
      "Python 3.11": [
        "getencoding"
      ]
    }
  },
  "logging": {
    "added": {
      "Python 3.1": [
        "handlers.NullHandler"
      ],
      "Python 3.2": [
        "lastResort",
        "getLogRecordFactory",
        "setLogRecordFactory",
        "config.dictConfig",
        "handlers.QueueHandler",
        "handlers.QueueListener"
      ],
      "Python 3.11": [
        "getLevelNamesMapping"
      ]
    }
  },
  "logging.config": {
    "added": {
      "Python 3.2": [
        "dictConfig"
      ]
    }
  },
  "logging.handlers": {
    "added": {
      "Python 3.1": [
        "NullHandler"
      ],
      "Python 3.2": [
        "QueueHandler",
        "QueueListener"
      ]
    }
  },
  "lzma": {
    "created": "Python 3.3"
  },
  "math": {
    "added": {
      "Python 3.2": [
        "isfinite",
        "expm1",
        "erf",
        "erfc",
        "gamma",
        "lgamma"
      ],
      "Python 3.3": [
        "log2"
      ],
      "Python 3.5": [
        "gcd",
        "inf",
        "nan",
        "isclose"
      ],
      "Python 3.6": [
        "tau"
      ],
      "Python 3.7": [
        "remainder"
      ],
      "Python 3.8": [
        "dist",
        "prod",
        "perm",
        "comb",
        "isqrt"
      ],
      "Python 3.9": [
        "lcm",
        "nextafter",
        "ulp"
      ],
      "Python 3.11": [
        "cbrt",
        "exp2"
      ],
      "Python 3.12": [
        "sumprod"
      ]
    }
  },
  "mmap": {
    "added": {
      "Python 3.8": [
        "MADV_NORMAL",
        "MADV_RANDOM",
        "MADV_SEQUENTIAL",
        "MADV_WILLNEED",
        "MADV_DONTNEED",
        "MADV_REMOVE",
        "MADV_DONTFORK",
        "MADV_DOFORK",
        "MADV_HWPOISON",
        "MADV_MERGEABLE",
        "MADV_UNMERGEABLE",
        "MADV_SOFT_OFFLINE",
        "MADV_HUGEPAGE",
        "MADV_NOHUGEPAGE",
        "MADV_DONTDUMP",
        "MADV_DODUMP",
        "MADV_FREE",
        "MADV_NOSYNC",
        "MADV_AUTOSYNC",
        "MADV_NOCORE",
        "MADV_CORE",
        "MADV_PROTECT",
        "MADV_FREE_REUSABLE",
        "MADV_FREE_REUSE"
      ],
      "Python 3.10": [
        "MAP_POPULATE"
      ],
      "Python 3.11": [
        "MAP_STACK"
      ]
    }
  },
  "multiprocessing": {
    "added": {
      "Python 3.3": [
        "Barrier"
      ],
      "Python 3.4": [
        "get_all_start_methods",
        "get_context",
        "get_start_method",
        "set_start_method"
      ],
      "Python 3.8": [
        "parent_process",
        "shared_memory"
      ]
    }
  },
  "multiprocessing.connection": {
    "added": {
      "Python 3.3": [
        "wait"
      ]
    }
  },
  "multiprocessing.shared_memory": {
    "created": "Python 3.8"
  },
  "nntplib": {
    "added": {
      "Python 3.2": [
        "NNTP_SSL"
      ]
    }
  },
  "operator": {
    "added": {
      "Python 3.4": [
        "length_hint"
      ],
      "Python 3.5": [
        "imatmul",
        "matmul"
      ],
      "Python 3.11": [
        "call"
      ]
    }
  },
  "os": {
    "added": {
      "Python 3.2": [
        "environb",
        "fsencode",
        "fsdecode",
        "getenvb",
        "get_exec_path",
        "getresuid",
        "setresuid",
        "getresgid",
        "setresgid",
        "initgroups",
        "supports_bytes_environ"
      ],
      "Python 3.3": [
        "CLD_EXITED",
        "CLD_KILLED",
        "CLD_DUMPED",
        "CLD_TRAPPED",
        "CLD_STOPPED",
        "CLD_CONTINUED",
        "F_LOCK",
        "F_TLOCK",
        "F_ULOCK",
        "F_TEST",
        "POSIX_FADV_NORMAL",
        "POSIX_FADV_SEQUENTIAL",
        "POSIX_FADV_RANDOM",
        "POSIX_FADV_NOREUSE",
        "POSIX_FADV_WILLNEED",
        "POSIX_FADV_DONTNEED",
        "PRIO_PROCESS",
        "PRIO_PGRP",
        "PRIO_USER",
        "P_ALL",
        "P_PID",
        "P_PGID",
        "RTLD_LAZY",
        "RTLD_NOW",
        "RTLD_GLOBAL",
        "RTLD_LOCAL",
        "RTLD_NODELETE",
        "RTLD_NOLOAD",
        "RTLD_DEEPBIND",
        "SCHED_OTHER",
        "SCHED_BATCH",
        "SCHED_IDLE",
        "SCHED_SPORADIC",
        "SCHED_FIFO",
        "SCHED_RR",
        "SCHED_RESET_ON_FORK",
        "SEEK_DATA",
        "SEEK_HOLE",
        "SF_NODISKIO",
        "SF_MNOWAIT",
        "SF_SYNC",
        "WEXITED",
        "WSTOPPED",
        "WNOWAIT",
        "XATTR_SIZE_MAX",
        "XATTR_CREATE",
        "XATTR_REPLACE",
        "getgrouplist",
        "getpriority",
        "setpriority",
        "getxattr",
        "setxattr",
        "listxattr",
        "removexattr",
        "get_terminal_size",
        "terminal_size",
        "fwalk",
        "lockf",
        "pipe2",
        "posix_fallocate",
        "posix_fadvise",
        "pread",
        "pwrite",
        "readv",
        "writev",
        "replace",
        "rmdir",
        "sched_param",
        "sched_get_priority_min",
        "sched_get_priority_max",
        "sched_setscheduler",
        "sched_getscheduler",
        "sched_setparam",
        "sched_getparam",
        "sched_rr_get_interval",
        "sched_yield",
        "sched_setaffinity",
        "sched_getaffinity",
        "sendfile",
        "supports_dir_fd",
        "supports_effective_ids",
        "supports_fd",
        "supports_follow_symlinks",
        "sync",
        "truncate",
        "unlink",
        "waitid"
      ],
      "Python 3.4": [
        "cpu_count",
        "get_inheritable",
        "set_inheritable",
        "get_handle_inheritable",
        "set_handle_inheritable"
      ],
      "Python 3.5": [
        "DirEntry",
        "scandir",
        "get_blocking",
        "set_blocking",
        "path.commonpath"
      ],
      "Python 3.6": [
        "GRND_NONBLOCK",
        "GRND_RANDOM",
        "PathLike",
        "fspath",
        "getrandom"
      ],
      "Python 3.7": [
        "RWF_NOWAIT",
        "RWF_HIPRI",
        "RWF_DSYNC",
        "RWF_SYNC",
        "preadv",
        "pwritev",
        "register_at_fork"
      ],
      "Python 3.8": [
        "MFD_CLOEXEC",
        "MFD_ALLOW_SEALING",
        "MFD_HUGETLB",
        "MFD_HUGE_SHIFT",
        "MFD_HUGE_MASK",
        "MFD_HUGE_64KB",
        "MFD_HUGE_512KB",
        "MFD_HUGE_1MB",
        "MFD_HUGE_2MB",
        "MFD_HUGE_8MB",
        "MFD_HUGE_16MB",
        "MFD_HUGE_32MB",
        "MFD_HUGE_256MB",
        "MFD_HUGE_512MB",
        "MFD_HUGE_1GB",
        "MFD_HUGE_2GB",
        "MFD_HUGE_16GB",
        "add_dll_directory",
        "copy_file_range",
        "memfd_create",
        "posix_spawn",
        "posix_spawnp"
      ],
      "Python 3.9": [
        "CLD_KILLED",
        "CLD_STOPPED",
        "P_PIDFD",
        "pidfd_open",
        "putenv",
        "unsetenv",
        "waitstatus_to_exitcode"
      ],
      "Python 3.10": [
        "EFD_CLOEXEC",
        "EFD_NONBLOCK",
        "EFD_SEMAPHORE",
        "O_EVTONLY",
        "O_FSYNC",
        "O_SYMLINK",
        "O_NOFOLLOW_ANY",
        "RWF_APPEND",
        "SPLICE_F_MOVE",
        "SPLICE_F_NONBLOCK",
        "SPLICE_F_MORE",
        "eventfd",
        "eventfd_read",
        "eventfd_write",
        "splice"
      ],
      "Python 3.11": [
        "SF_NOCACHE",
        "login_tty"
      ],
      "Python 3.12": [
        "PIDFD_NONBLOCK",
        "path.isjunction",
        "path.splitroot"
      ]
    }
  },
  "os.path": {
    "added": {
      "Python 3.5": [
        "commonpath"
      ],
      "Python 3.12": [
        "isjunction",
        "splitroot"
      ]
    }
  },
  "pathlib": {
    "created": "Python 3.4"
  },
  "pickle": {
    "added": {
      "Python 3.8": [
        "PickleBuffer"
      ]
    }
  },
  "pkgutil": {
    "added": {
      "Python 3.6": [
        "ModuleInfo"
      ],
      "Python 3.9": [
        "resolve_name"
      ]
    }
  },
  "platform": {
    "added": {
      "Python 3.8": [
        "win32_edition",
        "win32_is_iot"
      ],
      "Python 3.10": [
        "freedesktop_os_release"
      ]
    }
  },
  "plistlib": {
    "added": {
      "Python 3.4": [
        "FMT_BINARY",
        "FMT_XML",
        "load",
        "loads",
        "dump",
        "dumps"
      ],
      "Python 3.8": [
        "UID"
      ]
    }
  },
  "pprint": {
    "added": {
      "Python 3.8": [
        "pp"
      ]
    }
  },
  "py_compile": {
    "added": {
      "Python 3.7": [
        "PycInvalidationMode"
      ]
    }
  },
  "queue": {
    "added": {
      "Python 3.7": [
        "SimpleQueue"
      ]
    }
  },
  "random": {
    "added": {
      "Python 3.6": [
        "choices"
      ],
      "Python 3.9": [
        "randbytes"
      ]
    }
  },
  "re": {
    "added": {
      "Python 3.4": [
        "fullmatch"
      ]
    }
  },
  "readline": {
    "added": {
      "Python 3.5": [
        "append_history_file"
      ],
      "Python 3.6": [
        "set_auto_history"
      ]
    }
  },
  "reprlib": {
    "added": {
      "Python 3.2": [
        "recursive_repr"
      ]
    }
  },
  "resource": {
    "added": {
      "Python 3.2": [
        "RUSAGE_THREAD"
      ],
      "Python 3.4": [
        "RLIMIT_MSGQUEUE",
        "RLIMIT_NICE",
        "RLIMIT_RTPRIO",
        "RLIMIT_RTTIME",
        "RLIMIT_SIGPENDING",
        "RLIMIT_SBSIZE",
        "RLIMIT_SWAP",
        "RLIMIT_NPTS",
        "prlimit"
      ],
      "Python 3.10": [
        "RLIMIT_KQUEUES"
      ]
    }
  },
  "secrets": {
    "created": "Python 3.6"
  },
  "select": {
    "added": {
      "Python 3.2": [
        "PIPE_BUF"
      ],
      "Python 3.3": [
        "devpoll"
      ],
      "Python 3.6": [
        "EPOLLEXCLUSIVE"
      ]
    }
  },
  "selectors": {
    "created": "Python 3.4",
    "added": {
      "Python 3.5": [
        "DevpollSelector"
      ]
    }
  },
  "shlex": {
    "added": {
      "Python 3.3": [
        "quote"
      ],
      "Python 3.8": [
        "join"
      ]
    }
  },
  "shutil": {
    "added": {
      "Python 3.2": [
        "get_archive_formats",
        "get_unpack_formats",
        "make_archive",
        "register_archive_format",
        "register_unpack_format",
        "unpack_archive",
        "unregister_archive_format",
        "unregister_unpack_format"
      ],
      "Python 3.3": [
        "chown",
        "disk_usage",
        "get_terminal_size",
        "rmtree.avoids_symlink_attacks",
        "which"
      ],
      "Python 3.4": [
        "SameFileError"
      ]
    }
  },
  "signal": {
    "added": {
      "Python 3.2": [
        "CTRL_C_EVENT",
        "CTRL_BREAK_EVENT"
      ],
      "Python 3.3": [
        "SIG_BLOCK",
        "SIG_UNBLOCK",
        "SIG_SETMASK",
        "pthread_kill",
        "pthread_sigmask",
        "sigpending",
        "sigwait",
        "sigwaitinfo",
        "sigtimedwait"
      ],
      "Python 3.5": [
        "Signals",
        "Handlers",
        "Sigmasks"
      ],
      "Python 3.8": [
        "strsignal",
        "valid_signals",
        "raise_signal"
      ],
      "Python 3.9": [
        "pidfd_send_signal"
      ],
      "Python 3.11": [
        "SIGSTKFLT"
      ]
    }
  },
  "site": {
    "added": {
      "Python 3.2": [
        "getsitepackages",
        "getuserbase",
        "getusersitepackages"
      ]
    }
  },
  "smtplib": {
    "added": {
      "Python 3.5": [
        "SMTPNotSupportedError"
      ]
    }
  },
  "socket": {
    "added": {
      "Python 3.2": [
        "SOCK_CLOEXEC",
        "SOCK_NONBLOCK"
      ],
      "Python 3.3": [
        "AF_RDS",
        "CMSG_LEN",
        "CMSG_SPACE",
        "fromshare",
        "if_nameindex",
        "if_nametoindex",
        "if_indextoname",
        "sethostname"
      ],
      "Python 3.4": [
        "AF_LINK",
        "CAN_BCM",
        "CAN_BCM_RX_CHANGED",
        "CAN_BCM_RX_DELETE",
        "CAN_BCM_RX_READ",
        "CAN_BCM_RX_SETUP",
        "CAN_BCM_RX_STATUS",
        "CAN_BCM_RX_TIMEOUT",
        "CAN_BCM_TX_DELETE",
        "CAN_BCM_TX_EXPIRED",
        "CAN_BCM_TX_READ",
        "CAN_BCM_TX_SEND",
        "CAN_BCM_TX_SETUP",
        "CAN_BCM_TX_STATUS"
      ],
      "Python 3.5": [
        "CAN_RAW_FD_FRAMES"
      ],
      "Python 3.6": [
        "AF_ALG",
        "SO_DOMAIN",
        "SO_PROTOCOL",
        "SO_PEERSEC",
        "SO_PASSSEC",
        "TCP_USER_TIMEOUT",
        "TCP_CONGESTION"
      ],
      "Python 3.7": [
        "AF_VSOCK",
        "CAN_ISOTP",
        "TCP_NOTSENT_LOWAT",
        "close"
      ],
      "Python 3.8": [
        "AF_QIPCRTR",
        "create_server",
        "has_dualstack_ipv6"
      ],
      "Python 3.9": [
        "CAN_RAW_JOIN_FILTERS",
        "CAN_J1939",
        "IPPROTO_UDPLITE",
        "send_fds",
        "recv_fds"
      ],
      "Python 3.11": [
        "SCM_CREDS2",
        "LOCAL_CREDS",
        "LOCAL_CREDS_PERSISTENT",
        "SO_INCOMING_CPU"
      ]
    }
  },
  "sqlite3": {
    "added": {
      "Python 3.11": [
        "Blob"
      ]
    }
  },
  "ssl": {
    "added": {
      "Python 3.2": [
        "HAS_SNI",
        "OPENSSL_VERSION",
        "OPENSSL_VERSION_INFO",
        "OPENSSL_VERSION_NUMBER",
        "OP_ALL",
        "OP_NO_SSLv2",
        "OP_NO_SSLv3",
        "OP_NO_TLSv1",
        "SSLContext",
        "match_hostname"
      ],
      "Python 3.3": [
        "CHANNEL_BINDING_TYPES",
        "HAS_ECDH",
        "HAS_NPN",
        "OP_CIPHER_SERVER_PREFERENCE",
        "OP_SINGLE_DH_USE",
        "OP_SINGLE_ECDH_USE",
        "OP_NO_COMPRESSION",
        "SSLZeroReturnError",
        "SSLWantReadError",
        "SSLWantWriteError",
        "SSLSyscallError",
        "SSLEOFError",
        "RAND_bytes",
        "RAND_pseudo_bytes"
      ],
      "Python 3.4": [
        "ALERT_DESCRIPTION_ACCESS_DENIED",
        "ALERT_DESCRIPTION_BAD_CERTIFICATE",
        "ALERT_DESCRIPTION_BAD_CERTIFICATE_HASH_VALUE",
        "ALERT_DESCRIPTION_BAD_CERTIFICATE_STATUS_RESPONSE",
        "ALERT_DESCRIPTION_BAD_RECORD_MAC",
        "ALERT_DESCRIPTION_CERTIFICATE_EXPIRED",
        "ALERT_DESCRIPTION_CERTIFICATE_REVOKED",
        "ALERT_DESCRIPTION_CERTIFICATE_UNKNOWN",
        "ALERT_DESCRIPTION_CERTIFICATE_UNOBTAINABLE",
        "ALERT_DESCRIPTION_CLOSE_NOTIFY",
        "ALERT_DESCRIPTION_DECODE_ERROR",
        "ALERT_DESCRIPTION_DECOMPRESSION_FAILURE",
        "ALERT_DESCRIPTION_DECRYPT_ERROR",
        "ALERT_DESCRIPTION_HANDSHAKE_FAILURE",
        "ALERT_DESCRIPTION_ILLEGAL_PARAMETER",
        "ALERT_DESCRIPTION_INSUFFICIENT_SECURITY",
        "ALERT_DESCRIPTION_INTERNAL_ERROR",
        "ALERT_DESCRIPTION_NO_RENEGOTIATION",
        "ALERT_DESCRIPTION_PROTOCOL_VERSION",
        "ALERT_DESCRIPTION_RECORD_OVERFLOW",
        "ALERT_DESCRIPTION_UNEXPECTED_MESSAGE",
        "ALERT_DESCRIPTION_UNKNOWN_CA",
        "ALERT_DESCRIPTION_UNKNOWN_PSK_IDENTITY",
        "ALERT_DESCRIPTION_UNRECOGNIZED_NAME",
        "ALERT_DESCRIPTION_UNSUPPORTED_CERTIFICATE",
        "ALERT_DESCRIPTION_UNSUPPORTED_EXTENSION",
        "ALERT_DESCRIPTION_USER_CANCELLED",
        "OP_NO_TLSv1_1",
        "OP_NO_TLSv1_2",
        "PROTOCOL_TLSv1_1",
        "PROTOCOL_TLSv1_2",
        "VERIFY_DEFAULT",
        "VERIFY_CRL_CHECK_LEAF",
        "VERIFY_CRL_CHECK_CHAIN",
        "VERIFY_X509_STRICT",
        "Purpose.SERVER_AUTH",
        "Purpose.CLIENT_AUTH",
        "create_default_context",
        "enum_certificates",
        "enum_crls",
        "get_default_verify_paths"
      ],
      "Python 3.5": [
        "HAS_ALPN",
        "VERIFY_X509_TRUSTED_FIRST",
        "MemoryBIO",
        "SSLObject"
      ],
      "Python 3.6": [
        "OP_NO_TICKET",
        "PROTOCOL_TLS",
        "PROTOCOL_TLS_CLIENT",
        "PROTOCOL_TLS_SERVER",
        "AlertDescription",
        "VerifyFlags",
        "SSLErrorNumber",
        "SSLSession"
      ],
      "Python 3.7": [
        "HAS_NEVER_CHECK_COMMON_NAME",
        "HAS_SSLv2",
        "HAS_SSLv3",
        "HAS_TLSv1",
        "HAS_TLSv1_1",
        "HAS_TLSv1_2",
        "HAS_TLSv1_3",
        "OP_NO_TLSv1_3",
        "OP_NO_RENEGOTIATION",
        "SSLCertVerificationError",
        "TLSVersion"
      ],
      "Python 3.8": [
        "OP_ENABLE_MIDDLEBOX_COMPAT"
      ],
      "Python 3.10": [
        "OP_IGNORE_UNEXPECTED_EOF",
        "VERIFY_ALLOW_PROXY_CERTS",
        "VERIFY_X509_PARTIAL_CHAIN"
      ]
    }
  },
  "stat": {
    "added": {
      "Python 3.3": [
        "filemode"
      ],
      "Python 3.4": [
        "S_IFDOOR",
        "S_IFPORT",
        "S_IFWHT",
        "S_ISDOOR",
        "S_ISPORT",
        "S_ISWHT"
      ],
      "Python 3.5": [
        "FILE_ATTRIBUTE_ARCHIVE",
        "FILE_ATTRIBUTE_COMPRESSED",
        "FILE_ATTRIBUTE_DEVICE",
        "FILE_ATTRIBUTE_DIRECTORY",
        "FILE_ATTRIBUTE_ENCRYPTED",
        "FILE_ATTRIBUTE_HIDDEN",
        "FILE_ATTRIBUTE_INTEGRITY_STREAM",
        "FILE_ATTRIBUTE_NORMAL",
        "FILE_ATTRIBUTE_NOT_CONTENT_INDEXED",
        "FILE_ATTRIBUTE_NO_SCRUB_DATA",
        "FILE_ATTRIBUTE_OFFLINE",
        "FILE_ATTRIBUTE_READONLY",
        "FILE_ATTRIBUTE_REPARSE_POINT",
        "FILE_ATTRIBUTE_SPARSE_FILE",
        "FILE_ATTRIBUTE_SYSTEM",
        "FILE_ATTRIBUTE_TEMPORARY",
        "FILE_ATTRIBUTE_VIRTUAL"
      ],
      "Python 3.8": [
        "IO_REPARSE_TAG_SYMLINK",
        "IO_REPARSE_TAG_MOUNT_POINT",
        "IO_REPARSE_TAG_APPEXECLIN"
      ]
    }
  },
  "statistics": {
    "created": "Python 3.4",
    "added": {
      "Python 3.6": [
        "harmonic_mean"
      ],
      "Python 3.8": [
        "NormalDist",
        "fmean",
        "geometric_mean",
        "multimode",
        "quantiles"
      ],
      "Python 3.10": [
        "covariance",
        "correlation",
        "linear_regression"
      ]
    }
  },
  "string": {
    "added": {
      "Python 3.11": [
        "get_identifiers",
        "is_valid"
      ]
    }
  },
  "struct": {
    "added": {
      "Python 3.4": [
        "iter_unpack"
      ]
    }
  },
  "subprocess": {
    "added": {
      "Python 3.2": [
        "check_output"
      ],
      "Python 3.3": [
        "DEVNULL",
        "SubprocessError",
        "TimeoutExpired"
      ],
      "Python 3.5": [
        "CompletedProcess",
        "run"
      ],
      "Python 3.7": [
        "ABOVE_NORMAL_PRIORITY_CLASS",
        "BELOW_NORMAL_PRIORITY_CLASS",
        "HIGH_PRIORITY_CLASS",
        "IDLE_PRIORITY_CLASS",
        "NORMAL_PRIORITY_CLASS",
        "REALTIME_PRIORITY_CLASS",
        "CREATE_NO_WINDOW",
        "DETACHED_PROCESS",
        "CREATE_DEFAULT_ERROR_MODE",
        "CREATE_BREAKAWAY_FROM_JOB"
      ],
      "Python 3.8": [
        "_USE_POSIX_SPAWN"
      ],
      "Python 3.11": [
        "_USE_VFORK"
      ]
    }
  },
  "sys": {
    "added": {
      "Python 3.1": [
        "float_repr_style",
        "int_info"
      ],
      "Python 3.2": [
        "_xoptions",
        "abi_flags",
        "hash_info",
        "getswitchinterval",
        "setswitchinterval"
      ],
      "Python 3.3": [
        "_debugmallocstats",
        "base_exec_prefix",
        "base_prefix",
        "implementation",
        "thread_info"
      ],
      "Python 3.4": [
        "__interactivehook__",
        "getallocatedblocks"
      ],
      "Python 3.5": [
        "is_finalizing"
      ],
      "Python 3.6": [
        "_enablelegacywindowsfsencoding",
        "getfilesystemencodeerrors",
        "get_asyncgen_hooks",
        "set_asyncgen_hooks"
      ],
      "Python 3.7": [
        "__breakpointhook__",
        "breakpointhook",
        "getandroidapilevel",
        "get_coroutine_origin_tracking_depth",
        "set_coroutine_origin_tracking_depth"
      ],
      "Python 3.8": [
        "__unraisablehook__",
        "audit",
        "addaudithook",
        "unraisablehook",
        "pycache_prefix"
      ],
      "Python 3.9": [
        "platlibdir"
      ],
      "Python 3.10": [
        "orig_argv",
        "stdlib_module_names"
      ],
      "Python 3.11": [
        "_emscripten_info",
        "exception",
        "get_int_max_str_digits",
        "set_int_max_str_digits"
      ],
      "Python 3.12": [
        "activate_stack_trampoline",
        "deactivate_stack_trampoline",
        "is_stack_trampoline_active"
      ]
    }
  },
  "sysconfig": {
    "created": "Python 3.2",
    "added": {
      "Python 3.10": [
        "_get_preferred_schemes",
        "get_default_scheme",
        "get_preferred_scheme"
      ]
    }
  },
  "tempfile": {
    "added": {
      "Python 3.2": [
        "TemporaryDirectory"
      ],
      "Python 3.5": [
        "gettempdirb",
        "gettempprefixb"
      ]
    }
  },
  "termios": {
    "added": {
      "Python 3.11": [
        "tcgetwinsize",
        "tcsetwinsize"
      ]
    }
  },
  "textwrap": {
    "added": {
      "Python 3.3": [
        "indent"
      ],
      "Python 3.4": [
        "shorten"
      ]
    }
  },
  "threading": {
    "added": {
      "Python 3.2": [
        "TIMEOUT_MAX",
        "Barrier"
      ],
      "Python 3.3": [
        "get_ident"
      ],
      "Python 3.4": [
        "main_thread"
      ],
      "Python 3.8": [
        "excepthook",
        "get_native_id"
      ],
      "Python 3.10": [
        "__excepthook__",
        "getprofile",
        "gettrace"
      ],
      "Python 3.12": [
        "settrace_all_threads",
        "setprofile_all_threads"
      ]
    }
  },
  "time": {
    "added": {
      "Python 3.3": [
        "CLOCK_REALTIME",
        "CLOCK_HIGHRES",
        "CLOCK_MONOTONIC",
        "CLOCK_MONOTONIC_RAW",
        "CLOCK_PROCESS_CPUTIME_ID",
        "CLOCK_THREAD_CPUTIME_ID",
        "clock_settime",
        "clock_gettime",
        "get_clock_info",
        "monotonic",
        "perf_counter",
        "process_time"
      ],
      "Python 3.7": [
        "CLOCK_BOOTTIME",
        "CLOCK_PROF",
        "CLOCK_UPTIME",
        "clock_gettime_ns",
        "clock_settime_ns",
        "monotonic_ns",
        "perf_counter_ns",
        "process_time_ns",
        "time_ns",
        "thread_time",
        "thread_time_ns",
        "pthread_getcpuclockid"
      ],
      "Python 3.8": [
        "CLOCK_UPTIME_RAW"
      ],
      "Python 3.9": [
        "CLOCK_TAI"
      ]
    }
  },
  "tokenize": {
    "added": {
      "Python 3.2": [
        "open"
      ]
    }
  },
  "tomllib": {
    "created": "Python 3.11"
  },
  "traceback": {
    "added": {
      "Python 3.4": [
        "clear_frames"
      ],
      "Python 3.5": [
        "TracebackException",
        "StackSummary",
        "FrameSummary",
        "walk_stack",
        "walk_tb"
      ]
    }
  },
  "tracemalloc": {
    "created": "Python 3.4",
    "added": {
      "Python 3.6": [
        "DomainFilter"
      ],
      "Python 3.9": [
        "reset_peak"
      ]
    }
  },
  "types": {
    "added": {
      "Python 3.3": [
        "MappingProxyType",
        "SimpleNamespace",
        "new_class",
        "prepare_class"
      ],
      "Python 3.4": [
        "DynamicClassAttribute"
      ],
      "Python 3.5": [
        "CoroutineType",
        "coroutine"
      ],
      "Python 3.6": [
        "AsyncGeneratorType"
      ],
      "Python 3.7": [
        "ClassMethodDescriptorType",
        "MethodDescriptorType",
        "MethodWrapperType",
        "WrapperDescriptorType",
        "resolve_bases"
      ],
      "Python 3.8": [
        "CellType"
      ],
      "Python 3.9": [
        "GenericAlias"
      ],
      "Python 3.10": [
        "EllipsisType",
        "NoneType",
        "NotImplementedType",
        "UnionType"
      ]
    }
  },
  "typing": {
    "created": "Python 3.5",
    "added": {
      "Python 3.6": [
        "TYPE_CHECKING",
        "ClassVar",
        "Collection",
        "ContextManager",
        "NewType"
      ],
      "Python 3.8": [
        "Final",
        "Literal",
        "Protocol",
        "SupportsIndex",
        "TypedDict",
        "final",
        "get_args",
        "get_origin",
        "runtime_checkable"
      ],
      "Python 3.9": [
        "Annotated"
      ],
      "Python 3.10": [
        "Concatenate",
        "ParamSpec",
        "ParamSpecArgs",
        "ParamSpecKwargs",
        "TypeAlias",
        "TypeGuard",
        "is_typeddict"
      ],
      "Python 3.11": [
        "LiteralString",
        "Never",
        "NotRequired",
        "Required",
        "Self",
        "TypeVarTuple",
        "Unpack",
        "assert_never",
        "assert_type",
        "get_overloads",
        "clear_overloads",
        "dataclass_transform",
        "reveal_type"
      ]
    }
  },
  "unicodedata": {
    "added": {
      "Python 3.8": [
        "is_normalized"
      ]
    }
  },
  "unittest": {
    "added": {
      "Python 3.1": [
        "SkipTest",
        "skip",
        "skipIf",
        "skipUnless",
        "expectedFailure"
      ],
      "Python 3.2": [
        "TextTestResult",
        "installHandler",
        "registerResult",
        "removeHandler",
        "removeResult"
      ],
      "Python 3.8": [
        "IsolatedAsyncioTestCase",
        "addModuleCleanup",
        "doModuleCleanups"
      ],
      "Python 3.11": [
        "enterModuleContext"
      ]
    }
  },
  "unittest.mock": {
    "created": "Python 3.3",
    "added": {
      "Python 3.7": [
        "seal"
      ],
      "Python 3.8": [
        "AsyncMock"
      ]
    }
  },
  "urllib.parse": {
    "added": {
      "Python 3.2": [
        "DefragResult",
        "DefragResultBytes",
        "ParseResultBytes",
        "SplitResultBytes"
      ]
    }
  },
  "urllib.request": {
    "added": {
      "Python 3.4": [
        "DataHandler"
      ],
      "Python 3.5": [
        "HTTPPasswordMgrWithPriorAuth"
      ],
      "Python 3.11": [
        "HTTPRedirectHandler.http_error_308"
      ]
    }
  },
  "uuid": {
    "added": {
      "Python 3.7": [
        "SafeUUID"
      ]
    }
  },
  "venv": {
    "created": "Python 3.3"
  },
  "weakref": {
    "added": {
      "Python 3.4": [
        "WeakMethod",
        "finalize"
      ]
    }
  },
  "winreg": {
    "added": {
      "Python 3.2": [
        "CreateKeyEx",
        "DeleteKeyEx"
      ],
      "Python 3.6": [
        "REG_QWORD",
        "REG_QWORD_LITTLE_ENDIAN"
      ]
    }
  },
  "wsgiref.handlers": {
    "added": {
      "Python 3.2": [
        "IISCGIHandler",
        "read_environ"
      ]
    }
  },
  "wsgiref.types": {
    "created": "Python 3.11"
  },
  "xml.etree.ElementTree": {
    "added": {
      "Python 3.2": [
        "fromstringlist",
        "tostringlist",
        "register_namespace"
      ],
      "Python 3.3": [
        "canonicalize"
      ],
      "Python 3.4": [
        "XMLPullParser"
      ],
      "Python 3.8": [
        "C14NWriterTarget"
      ],
      "Python 3.9": [
        "indent"
      ]
    }
  },
  "xml.parsers.expat.errors": {
    "added": {
      "Python 3.2": [
        "codes",
        "messages"
      ]
    }
  },
  "xml.sax.handler": {
    "added": {
      "Python 3.10": [
        "LexicalHandler"
      ]
    }
  },
  "zipapp": {
    "created": "Python 3.5"
  },
  "zipfile": {
    "added": {
      "Python 3.3": [
        "ZIP_BZIP2",
        "ZIP_LZMA"
      ],
      "Python 3.8": [
        "Path"
      ],
      "Python 3.11": [
        "ZipFile.mkdir"
      ]
    }
  },
  "zlib": {
    "added": {
      "Python 3.3": [
        "ZLIB_RUNTIME_VERSION"
      ]
    }
  },
  "zoneinfo": {
    "created": "Python 3.9"
  }
}
